fuse/__init__.py
fuse/__main__.py
fuse/__version__.py
fuse/args.py
fuse/cli.py
fuse/console.py
fuse/logger.py
fuse/utils/__init__.py
fuse/utils/classes.py
fuse/utils/files.py
fuse/utils/formatters.py
fuse/utils/generator.py
fuse_cli-1.2.2.dist-info/licenses/LICENSE
fuse_cli-1.2.2.dist-info/METADATA
fuse_cli-1.2.2.dist-info/WHEEL
fuse_cli-1.2.2.dist-info/entry_points.txt
fuse_cli-1.2.2.dist-info/top_level.txt
fuse_cli-1.2.2.dist-info/RECORD
