Metadata-Version: 2.4
Name: fuse-cli
Version: 1.2.2
Summary: Fuse: Customizable wordlist generator with advanced pattern.
Author-email: "Ryan R." <dev.richarlison@proton.me>
License: MIT
Requires-Python: >=3.10
License-File: LICENSE
Dynamic: license-file
